MANIFEST.in
README.rst
setup.py
django_foundation_filefield_widget.egg-info/PKG-INFO
django_foundation_filefield_widget.egg-info/SOURCES.txt
django_foundation_filefield_widget.egg-info/dependency_links.txt
django_foundation_filefield_widget.egg-info/not-zip-safe
django_foundation_filefield_widget.egg-info/top_level.txt
foundation_filefield_widget/__init__.py
foundation_filefield_widget/widgets.py
foundation_filefield_widget/locale/en/LC_MESSAGES/django.mo
foundation_filefield_widget/locale/en/LC_MESSAGES/django.po
foundation_filefield_widget/locale/fr/LC_MESSAGES/django.mo
foundation_filefield_widget/locale/fr/LC_MESSAGES/django.po
foundation_filefield_widget/static/foundation_filefield_widget/foundation-filefield.css
foundation_filefield_widget/static/foundation_filefield_widget/foundation-imagefield.css
foundation_filefield_widget/static/foundation_filefield_widget/img-placeholder.jpg
foundation_filefield_widget/templates/foundation_filefield_widget/foundation_filefield_widget.html
foundation_filefield_widget/templates/foundation_filefield_widget/foundation_imagefield_widget.html