Metadata-Version: 1.1
Name: django-foundation-filefield-widget
Version: 0.0.4
Summary: A form widget to style file inputs in a foundation fashion.
Home-page: https://github.com/PhilipGarnero/django-foundation-filefield-widget
Author: Philip Garnero
Author-email: philip.garnero@gmail.com
License: MIT
Platform: UNKNOWN
Classifier: Development Status :: 3 - Alpha
Classifier: Environment :: Web Environment
Classifier: Framework :: Django
Classifier: License :: OSI Approved :: MIT License
Classifier: Programming Language :: Python :: 2.7
Classifier: Topic :: Internet :: WWW/HTTP
Classifier: Topic :: Software Development :: Libraries :: Python Modules
